pyproject_deplister/__init__.py
pyproject_deplister/__main__.py
pyproject_deplister/_version.py
pyproject_deplister/utils.py
pyproject_deplister-0.1.2.dist-info/LICENSE
pyproject_deplister-0.1.2.dist-info/METADATA
pyproject_deplister-0.1.2.dist-info/WHEEL
pyproject_deplister-0.1.2.dist-info/entry_points.txt
pyproject_deplister-0.1.2.dist-info/top_level.txt
pyproject_deplister-0.1.2.dist-info/RECORD
