Metadata-Version: 2.1
Name: pyproject_deplister
Version: 0.1.2
Summary: pyproject-deplister is a Python package for extracting dependency information from pyproject.toml files and converting it into the format of a requirements.txt file. With its simple and intuitive interface, pyproject-deplister makes it easy to manage and track dependencies for your Python projects, ensuring that you have all the necessary packages installed and up-to-date.
Author-email: Célien Donzé <celien.donze@he-arc.ch>, Jonathan Guerne <jonathan.guerne@he-arc.ch>
License: MIT License
Keywords: dependencies,pyproject.toml,extractor,list,requirements.txt
Classifier: Development Status :: 3 - Alpha
Classifier: Intended Audience :: Developers
Classifier: License :: OSI Approved :: MIT License
Classifier: Programming Language :: Python :: 3
License-File: LICENSE
Requires-Dist: tomli
Provides-Extra: dev
Requires-Dist: pytest ; extra == 'dev'
Requires-Dist: build ; extra == 'dev'
Requires-Dist: twine ; extra == 'dev'
